britekit/__about__.py
britekit/__init__.py
britekit/cli.py
britekit/commands/__init__.py
britekit/commands/_analyze.py
britekit/commands/_analyze_db.py
britekit/commands/_audioset.py
britekit/commands/_calibrate.py
britekit/commands/_ckpt_ops.py
britekit/commands/_db_add.py
britekit/commands/_db_delete.py
britekit/commands/_dedup.py
britekit/commands/_embed.py
britekit/commands/_ensemble.py
britekit/commands/_extract.py
britekit/commands/_inat.py
britekit/commands/_init.py
britekit/commands/_pickle.py
britekit/commands/_plot.py
britekit/commands/_reextract.py
britekit/commands/_reports.py
britekit/commands/_search.py
britekit/commands/_train.py
britekit/commands/_tune.py
britekit/commands/_wav2mp3.py
britekit/commands/_xeno.py
britekit/commands/_youtube.py
britekit/core/__init__.py
britekit/core/analyzer.py
britekit/core/audio.py
britekit/core/audio_util.py
britekit/core/augmentation.py
britekit/core/base_config.py
britekit/core/config_loader.py
britekit/core/data_module.py
britekit/core/dataset.py
britekit/core/exceptions.py
britekit/core/pickler.py
britekit/core/plot.py
britekit/core/predictor.py
britekit/core/reextractor.py
britekit/core/trainer.py
britekit/core/tuner.py
britekit/core/util.py
britekit/models/base_model.py
britekit/models/bknet.py
britekit/models/bknet_base.py
britekit/models/dla.py
britekit/models/effnet.py
britekit/models/gernet.py
britekit/models/head_factory.py
britekit/models/hgnet.py
britekit/models/model_inspector.py
britekit/models/model_loader.py
britekit/models/timm_model.py
britekit/models/vovnet.py
britekit/occurrence_db/occurrence_data_provider.py
britekit/occurrence_db/occurrence_db.py
britekit/occurrence_db/occurrence_pickle.py
britekit/testing/base_tester.py
britekit/testing/per_block_tester.py
britekit/testing/per_recording_tester.py
britekit/testing/per_segment_tester.py
britekit/training_db/extractor.py
britekit/training_db/training_data_provider.py
britekit/training_db/training_db.py
britekit/install/data/classes.csv
britekit-0.13.1.dist-info/METADATA
britekit-0.13.1.dist-info/WHEEL
britekit-0.13.1.dist-info/entry_points.txt
britekit-0.13.1.dist-info/licenses/LICENSE.txt
britekit-0.13.1.dist-info/RECORD
