Metadata-Version: 2.4
Name: britekit
Version: 0.13.1
Summary: Core functions for bioacoustic recognizers.
Project-URL: Documentation, https://github.com/jhuus/BriteKit#readme
Project-URL: Issues, https://github.com/jhuus/BriteKit/issues
Project-URL: Source, https://github.com/jhuus/BriteKit
Author-email: Jan Huus <jhuus1@gmail.com>
License-Expression: MIT
License-File: LICENSE.txt
Classifier: Development Status :: 4 - Beta
Classifier: Programming Language :: Python
Classifier: Programming Language :: Python :: 3.8
Classifier: Programming Language :: Python :: 3.9
Classifier: Programming Language :: Python :: 3.10
Classifier: Programming Language :: Python :: 3.11
Classifier: Programming Language :: Python :: 3.12
Classifier: Programming Language :: Python :: Implementation :: CPython
Classifier: Programming Language :: Python :: Implementation :: PyPy
Requires-Python: >=3.8
Requires-Dist: click<8.3,>=8.1
Requires-Dist: faiss-cpu>=1.10
Requires-Dist: librosa<2.0,>=0.10
Requires-Dist: lightning<2.6,>=2.5
Requires-Dist: matplotlib<3.11,>=3.8
Requires-Dist: numpy<2.4,>=2.0
Requires-Dist: omegaconf<2.4,>=2.3
Requires-Dist: onnx<2.0,>=1.18
Requires-Dist: pandas<2.3,>=2.0
Requires-Dist: pyinaturalist<1.0,>=0.20
Requires-Dist: pytorch-lightning<2.6,>=2.5
Requires-Dist: scipy<2.0,>=1.13
Requires-Dist: soundfile<1.0,>=0.13
Requires-Dist: tensorboard<3.0,>=2.19
Requires-Dist: timm<2.0,>=1.0.17
Requires-Dist: torch<2.9,>=2.5
Requires-Dist: torchaudio<2.9,>=2.5
Requires-Dist: yt-dlp>=2025.6.25
